{
    "version": "1.0.0",
    "description": "Gowordle CLI",
    "homepage": "https://github.com/RaphaelAZ/go-wordle",
    "license": "MIT",
    "architecture": {
        "64bit": {
            "url": "https://github.com/RaphaelAZ/go-wordle/releases/download/v#Version#/gowordle_windows_amd64.zip",
            "hash": "sha256:..."
        }
    },
    "bin": "gowordle.exe",
    "autoupdate": {
        "architecture": {
            "64bit": {
                "url": "https://github.com/RaphaelAZ/go-wordle/releases/download/v#Version#/gowordle_windows_amd64.zip"
            }
        },
        "hash": {
            "url": "https://github.com/RaphaelAZ/go-wordle/releases/download/v#Version#/checksums.txt",
            "find": "gowordle_windows_amd64.zip\\s+(\\w+)"
        }
    }
}